Metadata-Version: 1.1
Name: cloudio-client-python
Version: 0.0.0
Summary: cloud.iO client package
Home-page: https://github.com/boozo-unlimited/cloudio-client-python
Author: HES-SO Valais, School of Engineering, Sion
Author-email: thomas.sterren@hevs.ch
License: MIT
Keywords: cloud.iO library IoT cloud client mqtt
Platform: UNKNOWN
Classifier: Development Status :: 3 - Alpha
Classifier: Intended Audience :: Developers
Classifier: Intended Audience :: Education
Classifier: Intended Audience :: Science/Research
Classifier: Intended Audience :: Information Technology
Classifier: Topic :: Software Development :: Libraries :: Python Modules
Classifier: License :: OSI Approved :: MIT License
Classifier: Programming Language :: Python :: 3.8
Classifier: Programming Language :: Python :: 3.9
Classifier: Operating System :: OS Independent
